pygsm7.py
pygsm7-1.0.4.dist-info/LICENSE.md
pygsm7-1.0.4.dist-info/METADATA
pygsm7-1.0.4.dist-info/WHEEL
pygsm7-1.0.4.dist-info/top_level.txt
pygsm7-1.0.4.dist-info/RECORD
